xsuite_kernels-0.1.1.dist-info/RECORD
xsuite_kernels-0.1.1.dist-info/LICENSE
xsuite_kernels-0.1.1.dist-info/WHEEL
xsuite_kernels-0.1.1.dist-info/entry_points.txt
xsuite_kernels-0.1.1.dist-info/top_level.txt
xsuite_kernels-0.1.1.dist-info/METADATA
xsuite_kernels/prebuild_kernels.py
xsuite_kernels/__init__.py
xsuite_kernels/kernel_definitions.py
xsuite_kernels/cli.py
xsuite_kernels/lib/default_xfields_no_config.json
xsuite_kernels/lib/only_xtrack_backtrack_frozen_energy.c
xsuite_kernels/lib/default_only_xtrack_no_config.json
xsuite_kernels/lib/default_xfields_frozen_energy.c
xsuite_kernels/lib/default_only_xtrack.cpython-310-darwin.so
xsuite_kernels/lib/default_only_xtrack_no_limit.c
xsuite_kernels/lib/default_xcoll.json
xsuite_kernels/lib/only_xtrack_with_synrad.json
xsuite_kernels/lib/default_xcoll_frozen_longitudinal.json
xsuite_kernels/lib/default_xcoll_no_config.cpython-310-darwin.so
xsuite_kernels/lib/default_xcoll_backtrack_no_limit.c
xsuite_kernels/lib/only_xtrack_with_synrad_kick_as_co.json
xsuite_kernels/lib/only_xtrack_non_tracking_kernels_no_config.json
xsuite_kernels/lib/default_xcoll_backtrack_no_limit.cpython-310-darwin.so
xsuite_kernels/lib/only_xtrack_frozen_energy.c
xsuite_kernels/lib/default_xcoll_no_limit.c
xsuite_kernels/lib/default_xcoll_frozen_longitudinal.c
xsuite_kernels/lib/default_only_xtrack_no_config.cpython-310-darwin.so
xsuite_kernels/lib/only_xtrack_non_tracking_kernels_no_config.cpython-310-darwin.so
xsuite_kernels/lib/only_xtrack_with_synrad_kick_as_co.c
xsuite_kernels/lib/default_only_xtrack_exact_drifts.json
xsuite_kernels/lib/only_xtrack_non_tracking_kernels.c
xsuite_kernels/lib/default_only_xtrack_backtrack.cpython-310-darwin.so
xsuite_kernels/lib/default_xcoll_backtrack_frozen_energy.c
xsuite_kernels/lib/default_xfields.c
xsuite_kernels/lib/only_xtrack_taper.json
xsuite_kernels/lib/default_xfields_no_config.cpython-310-darwin.so
xsuite_kernels/lib/default_xcoll_backtrack.json
xsuite_kernels/lib/default_xcoll_backtrack_frozen_energy.json
xsuite_kernels/lib/__init__.py
xsuite_kernels/lib/default_xfields_frozen_longitudinal.c
xsuite_kernels/lib/default_xcoll_backtrack.cpython-310-darwin.so
