Metadata-Version: 2.1
Name: xsuite-kernels
Version: 0.1.1
Summary: A package supplying binary kernels for Xsuite.
Author-email: Szymon Łopaciuk <szymon@lopaciuk.eu>
License:                                  Apache License
Requires-Python: >=3.8
License-File: LICENSE
Requires-Dist: xtrack==0.57.0
Requires-Dist: xfields==0.15.1
Requires-Dist: xcoll==0.3.5
Requires-Dist: xobjects==0.4.1
